infoblox_discovery/__init__.py
infoblox_discovery/__main__.py
infoblox_discovery/api.py
infoblox_discovery/cache.py
infoblox_discovery/collector.py
infoblox_discovery/environments.py
infoblox_discovery/exceptions.py
infoblox_discovery/file_service_discovery.py
infoblox_discovery/http_service_discovery.py
infoblox_discovery/infoblox_dhcp.py
infoblox_discovery/infoblox_dns_server.py
infoblox_discovery/infoblox_member.py
infoblox_discovery/infoblox_node.py
infoblox_discovery/infoblox_webendpoint.py
infoblox_discovery/infoblox_zone.py
infoblox_discovery/meta_naming.py
infoblox_discovery/metrics.py
infoblox_discovery/transform.py
infoblox_discovery-0.4.0.dist-info/LICENSE
infoblox_discovery-0.4.0.dist-info/METADATA
infoblox_discovery-0.4.0.dist-info/WHEEL
infoblox_discovery-0.4.0.dist-info/top_level.txt
infoblox_discovery-0.4.0.dist-info/RECORD
